wdl_aid/__init__.py
wdl_aid/wdl_aid.py
wdl_aid/templates/__init__.py
wdl_aid/templates/default.md.j2
WDL_AID-1.0.1.dist-info/LICENSE
WDL_AID-1.0.1.dist-info/METADATA
WDL_AID-1.0.1.dist-info/WHEEL
WDL_AID-1.0.1.dist-info/entry_points.txt
WDL_AID-1.0.1.dist-info/top_level.txt
WDL_AID-1.0.1.dist-info/RECORD
