Metadata-Version: 2.1
Name: WDL-AID
Version: 1.0.1
Summary: Automatic Input Documentation for WDL workflows
Home-page: https://github.com/biowdl/wdl-aid
Author: Leiden University Medical Center
Author-email: sasc@lumc.nl
License: MIT
Keywords: bioinformatics,WDL,documentation
Classifier: Programming Language :: Python :: 3 :: Only
Classifier: Programming Language :: Python :: 3
Classifier: Programming Language :: Python :: 3.6
Classifier: Programming Language :: Python :: 3.7
Classifier: Programming Language :: Python :: 3.8
Classifier: Programming Language :: Python :: 3.9
Classifier: Programming Language :: Python :: 3.10
Classifier: Programming Language :: Python :: 3.11
Classifier: Programming Language :: Python :: 3.12
Classifier: Development Status :: 5 - Production/Stable
Classifier: License :: OSI Approved :: MIT License
License-File: LICENSE
Requires-Dist: miniwdl >=1.0
Requires-Dist: jinja2
Requires-Dist: setuptools
